{
	"dt": {
		"si": {
			"wc": 19,
			"ist": false,
			"itw": true,
			"fws": 0,
			"wp": {
				"2": [0, 3, 6],
				"4": [0, 4, 8]
			},
			"orl": [0, 5, 6, 4, 0, 7, 4, 7, 6],
			"lw": {
				"2": 6.0,
				"4": 3.0
			},
			"irs": false,
			"gwt": 1,
			"ctw": 9.0,
			"pmt": null,
			"cwc": 1,
			"fstc": null,
			"pcwc": 1,
			"rwsp": {
				"2": 10.0,
				"4": 5.0
			},
			"hashr": "0:0;4;4#5;0;7#6;7;6#R#4#001020#MV#3.0#MT#1#R#6#001122#MV#3.0#MT#1#MG#9.0#",
			"fb": null,
			"ab": null,
			"ml": 2,
			"cs": 0.3,
			"rl": [0, 5, 6, 4, 0, 7, 4, 7, 6],
			"sid": "1887788585706257920",
			"psid": "1887788585706257920",
			"st": 1,
			"nst": 1,
			"pf": 1,
			"aw": 9.00,
			"wid": 0,
			"wt": "C",
			"wk": "0_C",
			"wbn": null,
			"wfg": null,
			"blb": 100015.00,
			"blab": 100012.00,
			"bl": 100021.00,
			"tb": 3.00,
			"tbb": 3.00,
			"tw": 9.00,
			"np": 6.00,
			"ocr": null,
			"mr": null,
			"ge": [1, 11]
		}
	},
	"err": null
}